vectorpy/__init__.py
vectorpy/vector.py
vectorpy-1.5.dist-info/DESCRIPTION.rst
vectorpy-1.5.dist-info/METADATA
vectorpy-1.5.dist-info/RECORD
vectorpy-1.5.dist-info/WHEEL
vectorpy-1.5.dist-info/metadata.json
vectorpy-1.5.dist-info/top_level.txt
