Metadata-Version: 2.0
Name: vectorpy
Version: 1.5
Summary: Basic 3 Vector Object
Home-page: https://github.com/tboudreaux/vectorpy.git
Author: Thomas Boudreaux
Author-email: thomas@boudreauxmail.com
License: MIT
Platform: UNKNOWN
Classifier: Development Status :: 4 - Beta
Classifier: Intended Audience :: Science/Research
Classifier: License :: OSI Approved :: MIT License
Classifier: Programming Language :: Python :: 3
Requires-Dist: numpy (>=1.12.0)
